Metadata-Version: 1.1
Name: georgeredis
Version: 0.0.2
Summary: redis wrapper
Home-page: https://github.com/GeorgeWang1994/GRedis
Author: GeorgeWang1994
Author-email: georgewang1994@163.com
License: BSD
Platform: UNKNOWN
Classifier: Development Status :: 4 - Beta
Classifier: Intended Audience :: Developers
Classifier: License :: OSI Approved :: BSD License
Classifier: Operating System :: POSIX
Classifier: Programming Language :: Python
Classifier: Topic :: System :: Distributed Computing
Classifier: Topic :: Software Development :: Object Brokering
